client/client.py
models/__init__.py
models/agent.py
models/json_rpc.py
models/request.py
models/task.py
server/__init__.py
server/server.py
server/task_manager.py
utilities/agent_connect.py
utilities/consul_agent.py
utilities/consul_discovery.py
utilities/discovery.py
consul_ai_agent_sdk-0.1.1.dist-info/METADATA
consul_ai_agent_sdk-0.1.1.dist-info/WHEEL
consul_ai_agent_sdk-0.1.1.dist-info/top_level.txt
consul_ai_agent_sdk-0.1.1.dist-info/RECORD
